sonivis_lens_widget/__init__.py
sonivis_lens_widget/_frontend.py
sonivis_lens_widget/_version.py
sonivis_lens_widget/lens_widget.py
sonivis_lens_widget/labextension/build_log.json
sonivis_lens_widget/labextension/package.json
sonivis_lens_widget/labextension/static/lib_index_js.1cadbce7b2ff683562d9.js
sonivis_lens_widget/labextension/static/lib_index_js.1cadbce7b2ff683562d9.js.map
sonivis_lens_widget/labextension/static/lib_index_js.ff8400f68147b5dba0f1.js
sonivis_lens_widget/labextension/static/lib_index_js.ff8400f68147b5dba0f1.js.map
sonivis_lens_widget/labextension/static/lib_plugin_js.5a4cf3b8552eeeecbc4f.js
sonivis_lens_widget/labextension/static/lib_plugin_js.5a4cf3b8552eeeecbc4f.js.map
sonivis_lens_widget/labextension/static/lib_plugin_js.bb4337736acfd02b99a1.js
sonivis_lens_widget/labextension/static/lib_plugin_js.bb4337736acfd02b99a1.js.map
sonivis_lens_widget/labextension/static/lib_widget_js.008459affa49d4fe65e8.js
sonivis_lens_widget/labextension/static/lib_widget_js.008459affa49d4fe65e8.js.map
sonivis_lens_widget/labextension/static/lib_widget_js.00dbaff7d7c856a1403c.js
sonivis_lens_widget/labextension/static/lib_widget_js.00dbaff7d7c856a1403c.js.map
sonivis_lens_widget/labextension/static/lib_widget_js.08f1db779bf4fc3e99c0.js
sonivis_lens_widget/labextension/static/lib_widget_js.08f1db779bf4fc3e99c0.js.map
sonivis_lens_widget/labextension/static/lib_widget_js.0a77305c374be8ee2ba0.js
sonivis_lens_widget/labextension/static/lib_widget_js.0a77305c374be8ee2ba0.js.map
sonivis_lens_widget/labextension/static/lib_widget_js.0b0899b4ee292aa7ea0d.js
sonivis_lens_widget/labextension/static/lib_widget_js.0b0899b4ee292aa7ea0d.js.map
sonivis_lens_widget/labextension/static/lib_widget_js.0d1cfbed0386cbb3a872.js
sonivis_lens_widget/labextension/static/lib_widget_js.0d1cfbed0386cbb3a872.js.map
sonivis_lens_widget/labextension/static/lib_widget_js.103386cdec1fd1c11e27.js
sonivis_lens_widget/labextension/static/lib_widget_js.103386cdec1fd1c11e27.js.map
sonivis_lens_widget-0.1.4.dev0.dist-info/LICENSE.txt
sonivis_lens_widget-0.1.4.dev0.dist-info/METADATA
sonivis_lens_widget-0.1.4.dev0.dist-info/WHEEL
sonivis_lens_widget-0.1.4.dev0.dist-info/top_level.txt
sonivis_lens_widget-0.1.4.dev0.dist-info/RECORD
